{
    "Items": [
        {
            "brand_name": {
                "S": "貝出汁 中華そば"
            },
            "client_name": {
                "S": "株式会社テイクユー"
            },
            "id": {
                "S": "ST00061"
            },
            "name": {
                "S": "竹祥"
            }
        },
        {
            "brand_name": {
                "S": "株式会社スモールズ"
            },
            "client_name": {
                "S": "株式会社スモールズ"
            },
            "id": {
                "S": "ST00102"
            },
            "name": {
                "S": "ディストピアBar KARMA　カルマ"
            }
        },
        {
            "brand_name": {
                "S": "焼肉男"
            },
            "client_name": {
                "S": "株式会社オン・ザ・プラネット"
            },
            "id": {
                "S": "ST00052"
            },
            "name": {
                "S": "マンモス"
            }
        },
        {
            "brand_name": {
                "S": "株式会社FELICE"
            },
            "client_name": {
                "S": "株式会社FELICE"
            },
            "id": {
                "S": "ST00122"
            },
            "name": {
                "S": "宮崎辛麺　辛麺屋一輪"
            }
        },
        {
            "brand_name": {
                "S": "MASSIMOTTVIO"
            },
            "client_name": {
                "S": "株式会社2M8"
            },
            "id": {
                "S": "ST00107"
            },
            "name": {
                "S": "MASSIMOTTVIO"
            }
        },
        {
            "brand_name": {
                "S": "ニーハオ"
            },
            "client_name": {
                "S": "ニーハオ食品株式会社"
            },
            "id": {
                "S": "ST00083"
            },
            "name": {
                "S": "神田店"
            }
        },
        {
            "brand_name": {
                "S": "泡盛と沖縄地料理 龍泉"
            },
            "client_name": {
                "S": "JCC株式会社"
            },
            "id": {
                "S": "ST00043"
            },
            "name": {
                "S": "ラゾーナ川崎店"
            }
        },
        {
            "brand_name": {
                "S": "魚豪商コダマ"
            },
            "client_name": {
                "S": "株式会社オン・ザ・プラネット"
            },
            "id": {
                "S": "ST00049"
            },
            "name": {
                "S": "錦糸町店"
            }
        },
        {
            "brand_name": {
                "S": "エノテカ　ドォーロ"
            },
            "client_name": {
                "S": "メティウスフーズ"
            },
            "id": {
                "S": "ST00042"
            },
            "name": {
                "S": "平河町店"
            }
        },
        {
            "brand_name": {
                "S": "日本橋玉ゐ本店"
            },
            "client_name": {
                "S": "株式会社バレンタインブルーコーポレーション"
            },
            "id": {
                "S": "ST00136"
            },
            "name": {
                "S": "日本橋玉ゐ本店"
            }
        },
        {
            "brand_name": {
                "S": "焼肉 松の屋"
            },
            "client_name": {
                "S": "焼肉 松の屋"
            },
            "id": {
                "S": "ST00073"
            },
            "name": {
                "S": "焼肉 松の屋"
            }
        },
        {
            "brand_name": {
                "S": "土風炉"
            },
            "client_name": {
                "S": "株式会社ラムラ"
            },
            "id": {
                "S": "ST00108"
            },
            "name": {
                "S": "すし土風炉 登戸店"
            }
        },
        {
            "brand_name": {
                "S": "株式会社CatchBall"
            },
            "client_name": {
                "S": "株式会社CatchBall"
            },
            "id": {
                "S": "ST00074"
            },
            "name": {
                "S": "ようさい"
            }
        },
        {
            "brand_name": {
                "S": "カラオケパセラ"
            },
            "client_name": {
                "S": "株式会社ニュートン"
            },
            "id": {
                "S": "ST00089"
            },
            "name": {
                "S": "上野駅前店"
            }
        },
        {
            "brand_name": {
                "S": "合同会社SKTC"
            },
            "client_name": {
                "S": "合同会社SKTC"
            },
            "id": {
                "S": "ST00123"
            },
            "name": {
                "S": "Aphrodite　アフロディーテ（ニューハーフバー）"
            }
        },
        {
            "brand_name": {
                "S": "油そば 雷神"
            },
            "client_name": {
                "S": "株式会社雷神"
            },
            "id": {
                "S": "ST00116"
            },
            "name": {
                "S": "市川店"
            }
        },
        {
            "brand_name": {
                "S": "ホルモンのマンモス"
            },
            "client_name": {
                "S": "株式会社オン・ザ・プラネット"
            },
            "id": {
                "S": "ST00047"
            },
            "name": {
                "S": "ホルモンのマンモス"
            }
        },
        {
            "brand_name": {
                "S": "株式会社Plan・Do・See"
            },
            "client_name": {
                "S": "株式会社Plan・Do・See"
            },
            "id": {
                "S": "ST00062"
            },
            "name": {
                "S": "THE MARK GRAND HOTEL"
            }
        },
        {
            "brand_name": {
                "S": "魚豪商コダマ"
            },
            "client_name": {
                "S": "株式会社オン・ザ・プラネット"
            },
            "id": {
                "S": "ST00050"
            },
            "name": {
                "S": "新橋店"
            }
        },
        {
            "brand_name": {
                "S": "atomic BAR"
            },
            "client_name": {
                "S": "atomic BAR"
            },
            "id": {
                "S": "ST00129"
            },
            "name": {
                "S": "atomic BAR"
            }
        },
        {
            "brand_name": {
                "S": "炉端居酒屋"
            },
            "client_name": {
                "S": "株式会社まんてん"
            },
            "id": {
                "S": "ST00021"
            },
            "name": {
                "S": "中野製作所 まんてん別館"
            }
        },
        {
            "brand_name": {
                "S": "炭火焼きホルモンまんてん"
            },
            "client_name": {
                "S": "株式会社まんてん"
            },
            "id": {
                "S": "ST00018"
            },
            "name": {
                "S": "代々木店"
            }
        },
        {
            "brand_name": {
                "S": "肉汁屋"
            },
            "client_name": {
                "S": "株式会社ビック・バン"
            },
            "id": {
                "S": "ST00093"
            },
            "name": {
                "S": "新橋店"
            }
        },
        {
            "brand_name": {
                "S": "ニーハオ"
            },
            "client_name": {
                "S": "ニーハオ食品株式会社"
            },
            "id": {
                "S": "ST00082"
            },
            "name": {
                "S": "大森店"
            }
        },
        {
            "brand_name": {
                "S": "FAST OYSTERS"
            },
            "client_name": {
                "S": "FAST OYSTERS"
            },
            "id": {
                "S": "ST00112"
            },
            "name": {
                "S": "神楽坂店"
            }
        },
        {
            "brand_name": {
                "S": "株式会社マッスルボディメイク"
            },
            "client_name": {
                "S": "株式会社マッスルボディメイク"
            },
            "id": {
                "S": "ST00124"
            },
            "name": {
                "S": "マッスルボディメイク"
            }
        },
        {
            "brand_name": {
                "S": "北海道らーめん みそ熊"
            },
            "client_name": {
                "S": "株式会社 GRAST"
            },
            "id": {
                "S": "ST00086"
            },
            "name": {
                "S": "北千住店"
            }
        },
        {
            "brand_name": {
                "S": "株式会社アシュリップ"
            },
            "client_name": {
                "S": "株式会社アシュリップ"
            },
            "id": {
                "S": "ST00092"
            },
            "name": {
                "S": "カイロライン 国分寺整体院"
            }
        },
        {
            "brand_name": {
                "S": "楽が気"
            },
            "client_name": {
                "S": "株式会社ダイニングエッジ"
            },
            "id": {
                "S": "ST00075"
            },
            "name": {
                "S": "新橋本店"
            }
        },
        {
            "brand_name": {
                "S": "株式会社クラフトマスタージャパン"
            },
            "client_name": {
                "S": "株式会社クラフトマスタージャパン"
            },
            "id": {
                "S": "ST00028"
            },
            "name": {
                "S": "鮨 輝らく"
            }
        },
        {
            "brand_name": {
                "S": "ベトナムパレス船橋"
            },
            "client_name": {
                "S": "ベトナムパレス船橋"
            },
            "id": {
                "S": "ST00118"
            },
            "name": {
                "S": "ベトナムパレス船橋"
            }
        },
        {
            "brand_name": {
                "S": "新燻男"
            },
            "client_name": {
                "S": "株式会社オン・ザ・プラネット"
            },
            "id": {
                "S": "ST00055"
            },
            "name": {
                "S": "ニューイブシオ"
            }
        },
        {
            "brand_name": {
                "S": "カルニセリア"
            },
            "client_name": {
                "S": "株式会社goonies"
            },
            "id": {
                "S": "ST00132"
            },
            "name": {
                "S": "横浜店"
            }
        },
        {
            "brand_name": {
                "S": "ZANGIRI Next"
            },
            "client_name": {
                "S": "株式会社ZANGIRI"
            },
            "id": {
                "S": "ST00114"
            },
            "name": {
                "S": "ZANGIRI Next"
            }
        },
        {
            "brand_name": {
                "S": "株式会社PET’S MOST"
            },
            "client_name": {
                "S": "株式会社PET’S MOST"
            },
            "id": {
                "S": "ST00076"
            },
            "name": {
                "S": "inu to hito"
            }
        },
        {
            "brand_name": {
                "S": "元町 de 焼肉  DOURAKU"
            },
            "client_name": {
                "S": "株式会社たき航グループ"
            },
            "id": {
                "S": "ST00002"
            },
            "name": {
                "S": "横浜元町 de 焼肉DOURAKU(どうらく)"
            }
        },
        {
            "brand_name": {
                "S": "モンキーツリー"
            },
            "client_name": {
                "S": "株式会社エデュケーション"
            },
            "id": {
                "S": "ST00017"
            },
            "name": {
                "S": "モンキーツリー"
            }
        },
        {
            "brand_name": {
                "S": "ピッツェリア ドォーロ"
            },
            "client_name": {
                "S": "メティウスフーズ"
            },
            "id": {
                "S": "ST00041"
            },
            "name": {
                "S": "新橋店"
            }
        },
        {
            "brand_name": {
                "S": "日本橋 玉ゐ"
            },
            "client_name": {
                "S": "株式会社バレンタインブルーコーポレーション"
            },
            "id": {
                "S": "ST00003"
            },
            "name": {
                "S": "本店"
            }
        },
        {
            "brand_name": {
                "S": "デニーロ"
            },
            "client_name": {
                "S": "株式会社ティーアンドティー"
            },
            "id": {
                "S": "ST00007"
            },
            "name": {
                "S": "神田店"
            }
        },
        {
            "brand_name": {
                "S": "ニーハオ"
            },
            "client_name": {
                "S": "ニーハオ食品株式会社"
            },
            "id": {
                "S": "ST00079"
            },
            "name": {
                "S": "別館"
            }
        },
        {
            "brand_name": {
                "S": "武蔵野油学会"
            },
            "client_name": {
                "S": "株式会社ギガデイン"
            },
            "id": {
                "S": "ST00045"
            },
            "name": {
                "S": "代々木店"
            }
        },
        {
            "brand_name": {
                "S": "居酒屋ビッグ"
            },
            "client_name": {
                "S": "居酒屋ビッグ"
            },
            "id": {
                "S": "ST00046"
            },
            "name": {
                "S": "新河岸駅前店"
            }
        },
        {
            "brand_name": {
                "S": "炭火焼きホルモンまんてん"
            },
            "client_name": {
                "S": "株式会社まんてん"
            },
            "id": {
                "S": "ST00020"
            },
            "name": {
                "S": "中野店"
            }
        },
        {
            "brand_name": {
                "S": "大衆酒屋 てらけん本家"
            },
            "client_name": {
                "S": "株式会社テラケン"
            },
            "id": {
                "S": "ST00004"
            },
            "name": {
                "S": "https://www.notion.so泉岳寺駅前店"
            }
        },
        {
            "brand_name": {
                "S": "ワイン食堂がっと"
            },
            "client_name": {
                "S": "株式会社がっと"
            },
            "id": {
                "S": "ST00127"
            },
            "name": {
                "S": "渋谷円山町店"
            }
        },
        {
            "brand_name": {
                "S": "ピッツェリア ドォーロ"
            },
            "client_name": {
                "S": "メティウスフーズ"
            },
            "id": {
                "S": "ST00039"
            },
            "name": {
                "S": "麹町店"
            }
        },
        {
            "brand_name": {
                "S": "魚豪商コダマ"
            },
            "client_name": {
                "S": "株式会社オン・ザ・プラネット"
            },
            "id": {
                "S": "ST00048"
            },
            "name": {
                "S": "大井町店"
            }
        },
        {
            "brand_name": {
                "S": "韓美膳（ハンビジェ）"
            },
            "client_name": {
                "S": "株式会社 東亜フードサービス"
            },
            "id": {
                "S": "ST00033"
            },
            "name": {
                "S": "ルミネ立川"
            }
        },
        {
            "brand_name": {
                "S": "ラム肉専門店"
            },
            "client_name": {
                "S": "株式会社CatchBall"
            },
            "id": {
                "S": "ST00106"
            },
            "name": {
                "S": "隣のロッヂ"
            }
        },
        {
            "brand_name": {
                "S": "ロケ弁エージェント"
            },
            "client_name": {
                "S": "有限会社タカネット"
            },
            "id": {
                "S": "ST00119"
            },
            "name": {
                "S": "ロケ弁エージェント"
            }
        },
        {
            "brand_name": {
                "S": "韓美膳（ハンビジェ）"
            },
            "client_name": {
                "S": "株式会社 東亜フードサービス"
            },
            "id": {
                "S": "ST00032"
            },
            "name": {
                "S": "ららぽーと横浜"
            }
        },
        {
            "brand_name": {
                "S": "株式会社フードアンドパートナーズ"
            },
            "client_name": {
                "S": "株式会社フードアンドパートナーズ"
            },
            "id": {
                "S": "ST00117"
            },
            "name": {
                "S": "発酵デリカテッセンカフェテリアKouji&ko"
            }
        },
        {
            "brand_name": {
                "S": "富士屋本店"
            },
            "client_name": {
                "S": "株式会社ダイニング富士屋本店"
            },
            "id": {
                "S": "ST00070"
            },
            "name": {
                "S": "立呑 富士屋本店"
            }
        },
        {
            "brand_name": {
                "S": "株式会社スモールズ"
            },
            "client_name": {
                "S": "株式会社スモールズ"
            },
            "id": {
                "S": "ST00100"
            },
            "name": {
                "S": "Bar ANIME HOLIC アニメホリック goldengai"
            }
        },
        {
            "brand_name": {
                "S": "ゴーゴーカレー"
            },
            "client_name": {
                "S": "株式会社 ゴーゴーカレーグループ"
            },
            "id": {
                "S": "ST00072"
            },
            "name": {
                "S": "新宿東口駅前スタジアム"
            }
        },
        {
            "brand_name": {
                "S": "韓美膳（ハンビジェ）"
            },
            "client_name": {
                "S": "株式会社 東亜フードサービス"
            },
            "id": {
                "S": "ST00034"
            },
            "name": {
                "S": "ラゾーナ川崎"
            }
        },
        {
            "brand_name": {
                "S": "新潟カツ丼 タレカツ"
            },
            "client_name": {
                "S": "株式会社ラグーンインターナショナル"
            },
            "id": {
                "S": "ST00135"
            },
            "name": {
                "S": "渋谷店"
            }
        },
        {
            "brand_name": {
                "S": "株式会社スモールズ"
            },
            "client_name": {
                "S": "株式会社スモールズ"
            },
            "id": {
                "S": "ST00103"
            },
            "name": {
                "S": "オイスター&珍味 bar 不夜城"
            }
        },
        {
            "brand_name": {
                "S": "北海道らーめん みそ熊"
            },
            "client_name": {
                "S": "株式会社GRAST"
            },
            "id": {
                "S": "ST00085"
            },
            "name": {
                "S": "王子店"
            }
        },
        {
            "brand_name": {
                "S": "魚焼男"
            },
            "client_name": {
                "S": "株式会社オン・ザ・プラネット"
            },
            "id": {
                "S": "ST00054"
            },
            "name": {
                "S": "弐"
            }
        },
        {
            "brand_name": {
                "S": "魚無双"
            },
            "client_name": {
                "S": "株式会社オン・ザ・プラネット"
            },
            "id": {
                "S": "ST00051"
            },
            "name": {
                "S": "トオダ"
            }
        },
        {
            "brand_name": {
                "S": "立川酒場 魚丸"
            },
            "client_name": {
                "S": "H VIEW株式会社"
            },
            "id": {
                "S": "ST00044"
            },
            "name": {
                "S": "南口店"
            }
        },
        {
            "brand_name": {
                "S": "生ラムかんな"
            },
            "client_name": {
                "S": "株式会社ビック・バン"
            },
            "id": {
                "S": "ST00095"
            },
            "name": {
                "S": "新橋店"
            }
        },
        {
            "brand_name": {
                "S": "A’s ダーツバー(Darts Bar A's"
            },
            "client_name": {
                "S": "株式会社 Dart Ace"
            },
            "id": {
                "S": "ST00025"
            },
            "name": {
                "S": "神楽坂店"
            }
        },
        {
            "brand_name": {
                "S": "ホルモン屋 だん"
            },
            "client_name": {
                "S": "株式会社ビック・バン"
            },
            "id": {
                "S": "ST00098"
            },
            "name": {
                "S": "新橋総本店"
            }
        },
        {
            "brand_name": {
                "S": "ラムと泡"
            },
            "client_name": {
                "S": "株式会社ビック・バン"
            },
            "id": {
                "S": "ST00094"
            },
            "name": {
                "S": "本店"
            }
        },
        {
            "brand_name": {
                "S": "株式会社千寿菊"
            },
            "client_name": {
                "S": "株式会社千寿菊"
            },
            "id": {
                "S": "ST00099"
            },
            "name": {
                "S": "新橋バーラウンジ御殿"
            }
        },
        {
            "brand_name": {
                "S": "ニーハオ"
            },
            "client_name": {
                "S": "ニーハオ食品株式会社"
            },
            "id": {
                "S": "ST00084"
            },
            "name": {
                "S": "渋谷店"
            }
        },
        {
            "brand_name": {
                "S": "クアアイナ"
            },
            "client_name": {
                "S": "株式会社フォーシーズ"
            },
            "id": {
                "S": "ST00036"
            },
            "name": {
                "S": "渋谷店"
            }
        },
        {
            "brand_name": {
                "S": "新潟カツ丼 タレカツ"
            },
            "client_name": {
                "S": "株式会社ラグーンインターナショナル"
            },
            "id": {
                "S": "ST00134"
            },
            "name": {
                "S": "日比谷店"
            }
        },
        {
            "brand_name": {
                "S": "CRAFT CHEESE MARKET"
            },
            "client_name": {
                "S": "GOSSO株式会社"
            },
            "id": {
                "S": "ST00013"
            },
            "name": {
                "S": "渋谷駅前店"
            }
        },
        {
            "brand_name": {
                "S": "富士屋本店"
            },
            "client_name": {
                "S": "株式会社ダイニング富士屋本店"
            },
            "id": {
                "S": "ST00069"
            },
            "name": {
                "S": "日本橋浜町"
            }
        },
        {
            "brand_name": {
                "S": "分とく山"
            },
            "client_name": {
                "S": "株式会社とくやまホールディングス"
            },
            "id": {
                "S": "ST00031"
            },
            "name": {
                "S": "本店"
            }
        },
        {
            "brand_name": {
                "S": "A’s ダーツバー(Darts Bar A's"
            },
            "client_name": {
                "S": "株式会社 Dart Ace"
            },
            "id": {
                "S": "ST00023"
            },
            "name": {
                "S": "高円寺店"
            }
        },
        {
            "brand_name": {
                "S": "麺と肴　担々麺 ペン坊"
            },
            "client_name": {
                "S": "麺と肴　担々麺 ペン坊"
            },
            "id": {
                "S": "ST00029"
            },
            "name": {
                "S": "麺と肴　担々麺 ペン坊"
            }
        },
        {
            "brand_name": {
                "S": "Japrise"
            },
            "client_name": {
                "S": "Japrise"
            },
            "id": {
                "S": "ST00128"
            },
            "name": {
                "S": "片山鶏肉店"
            }
        },
        {
            "brand_name": {
                "S": "株式会社スモールズ"
            },
            "client_name": {
                "S": "株式会社スモールズ"
            },
            "id": {
                "S": "ST00101"
            },
            "name": {
                "S": "Japanese Bar　猪鹿蝶"
            }
        },
        {
            "brand_name": {
                "S": "0秒レモンサワー 仙台ホルモン焼肉酒場 ときわ亭"
            },
            "client_name": {
                "S": "GOSSO株式会社"
            },
            "id": {
                "S": "ST00011"
            },
            "name": {
                "S": "渋谷店"
            }
        },
        {
            "brand_name": {
                "S": "家庭料理居酒屋  焼肉Yakitaro"
            },
            "client_name": {
                "S": "家庭料理居酒屋  焼肉Yakitaro"
            },
            "id": {
                "S": "ST00088"
            },
            "name": {
                "S": "水道橋店"
            }
        },
        {
            "brand_name": {
                "S": "やきとり大吉"
            },
            "client_name": {
                "S": "ダイキチシステム㈱"
            },
            "id": {
                "S": "ST00121"
            },
            "name": {
                "S": "桜ヶ丘店"
            }
        },
        {
            "brand_name": {
                "S": "中華一番"
            },
            "client_name": {
                "S": "株式会社友進"
            },
            "id": {
                "S": "ST00009"
            },
            "name": {
                "S": "新小岩店"
            }
        },
        {
            "brand_name": {
                "S": "東京餃子楼"
            },
            "client_name": {
                "S": "株式会社パズルフードサービス"
            },
            "id": {
                "S": "ST00110"
            },
            "name": {
                "S": "工場"
            }
        },
        {
            "brand_name": {
                "S": "たまき新宿2代目店"
            },
            "client_name": {
                "S": "たまき新宿2代目店"
            },
            "id": {
                "S": "ST00071"
            },
            "name": {
                "S": "たまき新宿2代目店"
            }
        },
        {
            "brand_name": {
                "S": "CRAFTCHEESEMARKET"
            },
            "client_name": {
                "S": "株式会社GOSSO"
            },
            "id": {
                "S": "ST00087"
            },
            "name": {
                "S": "渋谷店"
            }
        },
        {
            "brand_name": {
                "S": "株式会社元気Dining"
            },
            "client_name": {
                "S": "株式会社元気Dining"
            },
            "id": {
                "S": "ST00058"
            },
            "name": {
                "S": "大衆寿司酒場 こがね商店"
            }
        },
        {
            "brand_name": {
                "S": "株式会社馬力"
            },
            "client_name": {
                "S": "株式会社馬力"
            },
            "id": {
                "S": "ST00065"
            },
            "name": {
                "S": "神田南口店"
            }
        },
        {
            "brand_name": {
                "S": "御座敷天婦羅　神楽坂 天孝"
            },
            "client_name": {
                "S": "御座敷天婦羅　神楽坂 天孝"
            },
            "id": {
                "S": "ST00105"
            },
            "name": {
                "S": "御座敷天婦羅　神楽坂 天孝"
            }
        },
        {
            "brand_name": {
                "S": "株式会社馬力"
            },
            "client_name": {
                "S": "株式会社馬力"
            },
            "id": {
                "S": "ST00066"
            },
            "name": {
                "S": "高円寺ガード下店"
            }
        },
        {
            "brand_name": {
                "S": "0秒レモンサワー 仙台ホルモン焼肉酒場 ときわ亭"
            },
            "client_name": {
                "S": "GOSSO株式会社"
            },
            "id": {
                "S": "ST00012"
            },
            "name": {
                "S": "池袋店"
            }
        },
        {
            "brand_name": {
                "S": "A’s ダーツバー(Darts Bar A's )"
            },
            "client_name": {
                "S": "株式会社 Dart Ace"
            },
            "id": {
                "S": "ST00026"
            },
            "name": {
                "S": "日本橋茅場町店"
            }
        },
        {
            "brand_name": {
                "S": "株式会社デイジイ"
            },
            "client_name": {
                "S": "株式会社デイジイ"
            },
            "id": {
                "S": "ST00014"
            },
            "name": {
                "S": "麹町店"
            }
        },
        {
            "brand_name": {
                "S": "クアアイナ"
            },
            "client_name": {
                "S": "株式会社フォーシーズ"
            },
            "id": {
                "S": "ST00035"
            },
            "name": {
                "S": "青山店"
            }
        },
        {
            "brand_name": {
                "S": "株式会社デイジイ"
            },
            "client_name": {
                "S": "株式会社デイジイ"
            },
            "id": {
                "S": "ST00015"
            },
            "name": {
                "S": "西新宿店"
            }
        },
        {
            "brand_name": {
                "S": "カラオケパセラ"
            },
            "client_name": {
                "S": "株式会社ニュートン"
            },
            "id": {
                "S": "ST00090"
            },
            "name": {
                "S": "上野御徒町店"
            }
        },
        {
            "brand_name": {
                "S": "ホルモン屋 だん"
            },
            "client_name": {
                "S": "株式会社ビック・バン"
            },
            "id": {
                "S": "ST00097"
            },
            "name": {
                "S": "新橋2号店"
            }
        },
        {
            "brand_name": {
                "S": "でですけ"
            },
            "client_name": {
                "S": "株式会社でですけ"
            },
            "id": {
                "S": "ST00115"
            },
            "name": {
                "S": "サイゴンキッチン"
            }
        },
        {
            "brand_name": {
                "S": "大勝軒"
            },
            "client_name": {
                "S": "株式会社エゴイプセ"
            },
            "id": {
                "S": "ST00068"
            },
            "name": {
                "S": "大勝軒まるいち 新宿東南口店"
            }
        },
        {
            "brand_name": {
                "S": "ニーハオ"
            },
            "client_name": {
                "S": "ニーハオ食品株式会社"
            },
            "id": {
                "S": "ST00081"
            },
            "name": {
                "S": "大井町店"
            }
        },
        {
            "brand_name": {
                "S": "0秒レモンサワー"
            },
            "client_name": {
                "S": "GOSSO株式会社"
            },
            "id": {
                "S": "ST00010"
            },
            "name": {
                "S": "池袋東口店"
            }
        },
        {
            "brand_name": {
                "S": "火鍋 小肥羊"
            },
            "client_name": {
                "S": "株式会社小肥羊ジャパン"
            },
            "id": {
                "S": "ST00016"
            },
            "name": {
                "S": "火鍋 小肥羊 銀座店"
            }
        },
        {
            "brand_name": {
                "S": "シュハスカリア キ ボン!"
            },
            "client_name": {
                "S": "シュハスカリア キ ボン!"
            },
            "id": {
                "S": "ST00133"
            },
            "name": {
                "S": "新虎通りcore店"
            }
        },
        {
            "brand_name": {
                "S": "東京餃子楼"
            },
            "client_name": {
                "S": "株式会社パズルフードサービス"
            },
            "id": {
                "S": "ST00111"
            },
            "name": {
                "S": "三軒茶屋本店"
            }
        },
        {
            "brand_name": {
                "S": "中華一番"
            },
            "client_name": {
                "S": "株式会社友進"
            },
            "id": {
                "S": "ST00008"
            },
            "name": {
                "S": "東陽町店"
            }
        },
        {
            "brand_name": {
                "S": "ホルモン屋 だん"
            },
            "client_name": {
                "S": "株式会社ビック・バン"
            },
            "id": {
                "S": "ST00096"
            },
            "name": {
                "S": "はなれ新橋3号店"
            }
        },
        {
            "brand_name": {
                "S": "株式会社友電設"
            },
            "client_name": {
                "S": "株式会社友電設"
            },
            "id": {
                "S": "ST00077"
            },
            "name": {
                "S": "Mahaloh Import Shop"
            }
        },
        {
            "brand_name": {
                "S": "板前寿司愛宕店"
            },
            "client_name": {
                "S": "板前寿司ジャパン"
            },
            "id": {
                "S": "ST00109"
            },
            "name": {
                "S": "板前寿司愛宕店"
            }
        },
        {
            "brand_name": {
                "S": "一般社団法人日本創世推進機構"
            },
            "client_name": {
                "S": "一般社団法人日本創世推進機構"
            },
            "id": {
                "S": "ST00104"
            },
            "name": {
                "S": "とんかつさくら"
            }
        },
        {
            "brand_name": {
                "S": "https://nikuya-takeuchi.com/"
            },
            "client_name": {
                "S": "株式会社肉屋たけうちコーポレーション"
            },
            "id": {
                "S": "ST00005"
            },
            "name": {
                "S": "蕨店"
            }
        },
        {
            "brand_name": {
                "S": "A’s ダーツバー(Darts Bar A's"
            },
            "client_name": {
                "S": "株式会社 Dart Ace"
            },
            "id": {
                "S": "ST00024"
            },
            "name": {
                "S": "水道橋店"
            }
        },
        {
            "brand_name": {
                "S": "合同会社FOOD GROOVE JAPAN"
            },
            "client_name": {
                "S": "合同会社FOOD GROOVE JAPAN"
            },
            "id": {
                "S": "ST00126"
            },
            "name": {
                "S": "米と魚　さかなさま"
            }
        },
        {
            "brand_name": {
                "S": "ニーハオ"
            },
            "client_name": {
                "S": "ニーハオ食品株式会社"
            },
            "id": {
                "S": "ST00080"
            },
            "name": {
                "S": "本店"
            }
        },
        {
            "brand_name": {
                "S": "ニクアザブ"
            },
            "client_name": {
                "S": "株式会社カワイハイ"
            },
            "id": {
                "S": "ST00113"
            },
            "name": {
                "S": "西麻布店"
            }
        },
        {
            "brand_name": {
                "S": "株式会社名店館"
            },
            "client_name": {
                "S": "株式会社名店館"
            },
            "id": {
                "S": "ST00125"
            },
            "name": {
                "S": "ビストロ エヴォルテ"
            }
        },
        {
            "brand_name": {
                "S": "炭火焼きホルモンまんてん"
            },
            "client_name": {
                "S": "株式会社まんてん"
            },
            "id": {
                "S": "ST00019"
            },
            "name": {
                "S": "中目黒本店"
            }
        },
        {
            "brand_name": {
                "S": "神奈川回転寿司ぐるめ亭"
            },
            "client_name": {
                "S": "株式会社マエザワフーズ"
            },
            "id": {
                "S": "ST00001"
            },
            "name": {
                "S": "西谷店"
            }
        },
        {
            "brand_name": {
                "S": "麺処いのこ"
            },
            "client_name": {
                "S": "合同会社いのこフード"
            },
            "id": {
                "S": "ST00063"
            },
            "name": {
                "S": "赤塚店"
            }
        },
        {
            "brand_name": {
                "S": "ニーハオ"
            },
            "client_name": {
                "S": "ニーハオ食品株式会社"
            },
            "id": {
                "S": "ST00078"
            },
            "name": {
                "S": "工場"
            }
        },
        {
            "brand_name": {
                "S": "とく山"
            },
            "client_name": {
                "S": "株式会社とくやまホールディングス"
            },
            "id": {
                "S": "ST00030"
            },
            "name": {
                "S": "とく山"
            }
        },
        {
            "brand_name": {
                "S": "株式会社元気Dining"
            },
            "client_name": {
                "S": "株式会社元気Dining"
            },
            "id": {
                "S": "ST00060"
            },
            "name": {
                "S": "大衆串焼き酒場こがね"
            }
        },
        {
            "brand_name": {
                "S": "神田小川町店"
            },
            "client_name": {
                "S": "ラフェス"
            },
            "id": {
                "S": "ST00120"
            },
            "name": {
                "S": "神田小川町店"
            }
        },
        {
            "brand_name": {
                "S": "株式会社元気Dining"
            },
            "client_name": {
                "S": "株式会社元気Dining"
            },
            "id": {
                "S": "ST00057"
            },
            "name": {
                "S": "大衆寿司酒場こがね"
            }
        },
        {
            "brand_name": {
                "S": "新魚焼男"
            },
            "client_name": {
                "S": "株式会社オン・ザ・プラネット"
            },
            "id": {
                "S": "ST00056"
            },
            "name": {
                "S": "ニューサカナヤキオ"
            }
        },
        {
            "brand_name": {
                "S": "PASTA of LIFE"
            },
            "client_name": {
                "S": "メティウスフーズ"
            },
            "id": {
                "S": "ST00040"
            },
            "name": {
                "S": "新宿店"
            }
        },
        {
            "brand_name": {
                "S": "クアアイナ"
            },
            "client_name": {
                "S": "株式会社フォーシーズ"
            },
            "id": {
                "S": "ST00037"
            },
            "name": {
                "S": "五反田店"
            }
        },
        {
            "brand_name": {
                "S": "らぁ麺はつ穂"
            },
            "client_name": {
                "S": "メティウスフーズ"
            },
            "id": {
                "S": "ST00038"
            },
            "name": {
                "S": "らぁ麺はつ穂"
            }
        },
        {
            "brand_name": {
                "S": "麵処いのこ"
            },
            "client_name": {
                "S": "合同会社いのこフード"
            },
            "id": {
                "S": "ST00064"
            },
            "name": {
                "S": "平和台店"
            }
        },
        {
            "brand_name": {
                "S": "カラオケパセラ"
            },
            "client_name": {
                "S": "株式会社ニュートン"
            },
            "id": {
                "S": "ST00091"
            },
            "name": {
                "S": "渋谷店"
            }
        },
        {
            "brand_name": {
                "S": "株式会社元気Dining"
            },
            "client_name": {
                "S": "株式会社元気Dining"
            },
            "id": {
                "S": "ST00059"
            },
            "name": {
                "S": "大衆焼肉酒場こがね"
            }
        },
        {
            "brand_name": {
                "S": "株式会社馬力"
            },
            "client_name": {
                "S": "株式会社馬力"
            },
            "id": {
                "S": "ST00067"
            },
            "name": {
                "S": "新橋店"
            }
        },
        {
            "brand_name": {
                "S": "魚焼男"
            },
            "client_name": {
                "S": "株式会社オン・ザ・プラネット"
            },
            "id": {
                "S": "ST00053"
            },
            "name": {
                "S": "新橋本店"
            }
        },
        {
            "brand_name": {
                "S": "A’s ダーツバー(Darts Bar A's )"
            },
            "client_name": {
                "S": "株式会社 Dart Ace"
            },
            "id": {
                "S": "ST00022"
            },
            "name": {
                "S": "大塚店"
            }
        },
        {
            "brand_name": {
                "S": "株式会社エイトシナジー"
            },
            "client_name": {
                "S": "株式会社エイトシナジー"
            },
            "id": {
                "S": "ST00027"
            },
            "name": {
                "S": "蕎麦割烹居酒屋　更科天狐"
            }
        },
        {
            "brand_name": {
                "S": "有限会社ティーアンドティー"
            },
            "client_name": {
                "S": "有限会社ティーアンドティー"
            },
            "id": {
                "S": "ST00006"
            },
            "name": {
                "S": "SMITH BURGER CLUB"
            }
        },
        {
            "brand_name": {
                "S": "中国料理 かおたん"
            },
            "client_name": {
                "S": "株式会社 東神"
            },
            "id": {
                "S": "ST00130"
            },
            "name": {
                "S": "赤坂店"
            }
        },
        {
            "brand_name": {
                "S": "丸鶏 るいすけ"
            },
            "client_name": {
                "S": "㈱ロイヤルストレートフラッシュ"
            },
            "id": {
                "S": "ST00131"
            },
            "name": {
                "S": "丸鶏 るいすけ"
            }
        }
    ],
    "Count": 136,
    "ScannedCount": 136,
    "ConsumedCapacity": null
}
